secret/SCRATCH.py
secret/__init__.py
tests/__init__.py
tests/__main__.py
tkutil/__init__.py
tkutil/__main__.py
tkutil/error/__init__.py
tkutil/hooking/__init__.py
tkutil/hooking/ante_build_hook.py
tkutil/hooking/ante_release_hook.py
tkutil/hooking/post_build_hook.py
tkutil/hooking/post_release_hook.py
tkutil/misc/__init__.py
tkutil/pyrustic_data/build_report.json
tkutil/pyrustic_data/hooking.json
tkutil/pyrustic_data/hubstore.json
tkutil/pyrustic_data/release_info.json
tkutil/pyrustic_data/backstage/config/build.json
tkutil/pyrustic_data/backstage/config/init.json
tkutil/pyrustic_data/backstage/config/release.json
tkutil/pyrustic_data/backstage/data/build_report.json
tkutil/pyrustic_data/backstage/data/github_release_form.json
tkutil/pyrustic_data/backstage/hooking/build.json
tkutil/pyrustic_data/backstage/hooking/init.json
tkutil/pyrustic_data/backstage/hooking/release.json
tkutil/pyrustic_data/backstage/report/build_report.json
tkutil/pyrustic_data/backstage/report/release_report.json
tkutil/pyrustic_data/hubstore/img.json
tkutil/pyrustic_data/hubstore/promotion.json
tkutil/window/__init__.py
tkutil-0.0.8.dist-info/LICENSE
tkutil-0.0.8.dist-info/METADATA
tkutil-0.0.8.dist-info/WHEEL
tkutil-0.0.8.dist-info/entry_points.txt
tkutil-0.0.8.dist-info/top_level.txt
tkutil-0.0.8.dist-info/RECORD
